bp_btc_com/__init__.py
bp_btc_com/explorer.py
bp_btc_com/util.py
bp_btc_com-0.0.5.dist-info/LICENSE
bp_btc_com-0.0.5.dist-info/METADATA
bp_btc_com-0.0.5.dist-info/WHEEL
bp_btc_com-0.0.5.dist-info/top_level.txt
bp_btc_com-0.0.5.dist-info/RECORD
