Metadata-Version: 2.1
Name: bp-btc-com
Version: 0.0.5
Summary: An api wrapper for btc.com block explorer api
Home-page: https://github.com/qlbnb/btc-com
Author: Joe Pasquantonio/Qiao Liang
Author-email: liang.qiao@binance.com
License: UNKNOWN
Platform: UNKNOWN
Classifier: Programming Language :: Python :: 3
Classifier: License :: OSI Approved :: MIT License
Classifier: Operating System :: OS Independent
Requires-Python: >=3
Requires-Dist: requests
